src/design/module_booth.v
module mult_with_no_fsm#(
    parameter N = 8
) (
    input logic clk,
    input logic rst,
    input logic [N-1:0] A,
    input logic [N-1:0] B,
    input logic load_A,               // Control de carga de A
    input logic load_B,               // Control de carga de B
    input logic load_add,             // Control para carga de adición
    input logic shift_HQ_LQ_Q_1,      // Control de desplazamiento
    input logic add_sub,              // Control de suma/resta
    output logic [1:0] Q_LSB,
    output logic [2*N-1:0] Y
);

logic [N-1:0] M;
logic [N-1:0] adder_sub_out;
logic [2*N:0] shift;
logic [N-1:0] HQ;
logic [N-1:0] LQ;
logic Q_1;

// Registro de M
always_ff @(posedge clk or negedge rst) begin
    if (!rst)
        M <= 'b0;
    else if (load_A)
        M <= A;
end

// Adición o sustracción
always_comb begin
    if (add_sub)
        adder_sub_out = M + HQ;
    else
        adder_sub_out = M - HQ;
end

// Registros de desplazamiento
always_comb begin
    Y = {HQ, LQ};
    HQ = shift[2*N:N+1];
    LQ = shift[N:1];
    Q_1 = shift[0];
    Q_LSB = {LQ[0], Q_1};
end

always_ff @(posedge clk or negedge rst) begin
    if (!rst)
        shift <= 'b0;
    else if (shift_HQ_LQ_Q_1)
        // Desplazamiento aritmético
        shift <= $signed(shift) >>> 1;
    else begin
        if (load_B)
            shift[N:1] <= B;
        if (load_add)
            shift[2*N:N+1] <= adder_sub_out;
    end
end

endmodule

src/sim/module_booth_tb.v
module tb_mult_with_no_fsm;

    // Parámetros
    parameter N = 8;

    // Señales de prueba
    logic clk;
    logic rst;
    logic [N-1:0] A;
    logic [N-1:0] B;
    logic load_A;
    logic load_B;
    logic load_add;
    logic shift_HQ_LQ_Q_1;
    logic add_sub;
    logic [1:0] Q_LSB;
    logic [2*N-1:0] Y;

    // Instanciación del módulo a probar
    mult_with_no_fsm #(.N(N)) uut (
        .clk(clk),
        .rst(rst),
        .A(A),
        .B(B),
        .load_A(load_A),
        .load_B(load_B),
        .load_add(load_add),
        .shift_HQ_LQ_Q_1(shift_HQ_LQ_Q_1),
        .add_sub(add_sub),
        .Q_LSB(Q_LSB),
        .Y(Y)
    );

    // Generador de reloj
    initial begin
        clk = 0;
        forever #5 clk = ~clk; // Generar un reloj de 10 unidades de tiempo
    end

    // Proceso de estímulo
    initial begin
        // Inicialización
        rst = 0;
        load_A = 0;
        load_B = 0;
        load_add = 0;
        shift_HQ_LQ_Q_1 = 0;
        add_sub = 0;
        A = 0;
        B = 0;

        // Aplicar un reset
        #10 rst = 1; // Habilitar el reset
        #10 rst = 0; // Deshabilitar el reset

        // Cargar A y B
        A = 8'b00001111; // 15 en decimal
        load_A = 1;
        #10 load_A = 0; // Deshabilitar carga de A

        B = 8'b00000011; // 3 en decimal
        load_B = 1;
        #10 load_B = 0; // Deshabilitar carga de B

        // Realizar una suma
        load_add = 1;
        add_sub = 1; // Sumar
        #10 load_add = 0; // Deshabilitar carga de suma

        // Shift
        shift_HQ_LQ_Q_1 = 1; // Desplazar
        #10 shift_HQ_LQ_Q_1 = 0; // Deshabilitar el desplazamiento

        // Realizar una resta
        load_add = 1;
        add_sub = 0; // Restar
        #10 load_add = 0; // Deshabilitar carga de resta

        // Otro desplazamiento
        shift_HQ_LQ_Q_1 = 1; // Desplazar
        #10 shift_HQ_LQ_Q_1 = 0; // Deshabilitar el desplazamiento

        // Finalizar la simulación
        #10 $finish;
    end

    // Monitoreo de señales
    initial begin
        $monitor("Time: %0t | A: %b | B: %b | Y: %b | Q_LSB: %b", $time, A, B, Y, Q_LSB);
    end
    // Monitorear la salida
    initial begin
        $dumpfile("tb_mult_with_no_fsm.vcd");
        $dumpvars(0, tb_mult_with_no_fsm);
        $monitor("Time: %0t ns | clk = %b | rst = %b | A = %d | B = %d | load_A = %b | load_B = %b | load_add = %b | shift_HQ_LQ_Q_1 = %b | add_sub = %b | Q_LSB = %b | Y = %d", 
                 $time, clk, rst, A, B, load_A, load_B, load_add, shift_HQ_LQ_Q_1, add_sub, Q_LSB, Y);
    end

endmodule

src/build/tb_mult_with_no_fsm.vcd
$date
	Mon Nov 04 13:25:08 2024
$end
$version
	Icarus Verilog
$end
$timescale
	1s
$end
$scope module tb_mult_with_no_fsm $end
$var wire 16 ! Y [15:0] $end
$var wire 2 " Q_LSB [1:0] $end
$var parameter 32 # N $end
$var reg 8 $ A [7:0] $end
$var reg 8 % B [7:0] $end
$var reg 1 & add_sub $end
$var reg 1 ' clk $end
$var reg 1 ( load_A $end
$var reg 1 ) load_B $end
$var reg 1 * load_add $end
$var reg 1 + rst $end
$var reg 1 , shift_HQ_LQ_Q_1 $end
$scope module uut $end
$var wire 8 - A [7:0] $end
$var wire 8 . B [7:0] $end
$var wire 1 & add_sub $end
$var wire 1 ' clk $end
$var wire 1 ( load_A $end
$var wire 1 ) load_B $end
$var wire 1 * load_add $end
$var wire 1 + rst $end
$var wire 1 , shift_HQ_LQ_Q_1 $end
$var parameter 32 / N $end
$var reg 8 0 HQ [7:0] $end
$var reg 8 1 LQ [7:0] $end
$var reg 8 2 M [7:0] $end
$var reg 1 3 Q_1 $end
$var reg 2 4 Q_LSB [1:0] $end
$var reg 16 5 Y [15:0] $end
$var reg 8 6 adder_sub_out [7:0] $end
$var reg 16 7 shift [15:0] $end
$upscope $end
$upscope $end
$enddefinitions $end
$comment Show the parameter values. $end
$dumpall
b1000 /
b1000 #
$end
#0
$dumpvars
bx 7
bx 6
bx 5
bx 4
x3
bx 2
bx 1
bx 0
b0 .
b0 -
0,
0+
0*
0)
0(
0'
0&
b0 %
b0 $
bx "
bx !
$end
#5
b0 "
b0 4
bx000000000000000 !
bx000000000000000 5
03
b0 1
bx0000000 0
b0 2
b0 7
1'
#10
0'
1+
#15
1'
#20
0'
1(
b1111 $
b1111 -
0+
#25
1'
#30
0'
1)
b11 %
b11 .
0(
#35
1'
#40
0'
1&
1*
0)
#45
1'
#50
0'
1,
0*
#55
1'
#60
0'
0&
1*
0,
#65
1'
#70
0'
1,
0*
#75
1'
#80
0'
0,
