src/design/module_booth.v
module mult_with_no_fsm#(
    parameter N = 8
) (
    input logic clk,
    input logic rst,
    input logic [N-1:0] A,
    input logic [N-1:0] B,
    input logic load_A,               // Control de carga de A
    input logic load_B,               // Control de carga de B
    input logic load_add,             // Control para carga de adición
    input logic shift_HQ_LQ_Q_1,      // Control de desplazamiento
    input logic add_sub,              // Control de suma/resta
    output logic [1:0] Q_LSB,
    output logic [2*N-1:0] Y
);

logic [N-1:0] M;
logic [N-1:0] adder_sub_out;
logic [2*N:0] shift;
logic [N-1:0] HQ;
logic [N-1:0] LQ;
logic Q_1;

// Registro de M
always_ff @(posedge clk or negedge rst) begin
    if (!rst)
        M <= 'b0;
    else if (load_A)
        M <= A;
end

// Adición o sustracción
always_comb begin
    if (add_sub)
        adder_sub_out = M + HQ;
    else
        adder_sub_out = M - HQ;
end

// Registros de desplazamiento
always_comb begin
    Y = {HQ, LQ};
    HQ = shift[2*N:N+1];
    LQ = shift[N:1];
    Q_1 = shift[0];
    Q_LSB = {LQ[0], Q_1};
end

always_ff @(posedge clk or negedge rst) begin
    if (!rst)
        shift <= 'b0;
    else if (shift_HQ_LQ_Q_1)
        // Desplazamiento aritmético
        shift <= $signed(shift) >>> 1;
    else begin
        if (load_B)
            shift[N:1] <= B;
        if (load_add)
            shift[2*N:N+1] <= adder_sub_out;
    end
end

endmodule

src/sim/module_booth_tb.v
`timescale 1ns/1ps

module tb_mult_with_no_fsm;
    parameter N = 12;  // Ancho de bits de entrada
    
    // Entradas del módulo
    logic clk;
    logic rst;
    logic [11:0] A, B;
    logic load_A;
    logic load_B;
    logic load_add;
    logic shift_HQ_LQ_Q_1;
    logic add_sub;
    
    // Salidas del módulo
    logic [1:0] Q_LSB;
    logic [23:0] Y;
    
    // Instancia del módulo a probar
    mult_with_no_fsm #(.N(N)) uut (
        .clk(clk),
        .rst(rst),
        .A(A),
        .B(B),
        .load_A(load_A),
        .load_B(load_B),
        .load_add(load_add),
        .shift_HQ_LQ_Q_1(shift_HQ_LQ_Q_1),
        .add_sub(add_sub),
        .Q_LSB(Q_LSB),
        .Y(Y)
    );
    
    // Generación del reloj
    always #5 clk = ~clk;  // Periodo de 10 ns (frecuencia de 100 MHz)
    
    // Monitor para observar el estado del sistema
    initial begin
        $monitor("Time: %0t ns | clk = %b | rst = %b | A = %d | B = %d | load_A = %b | load_B = %b | load_add = %b | shift_HQ_LQ_Q_1 = %b | add_sub = %b | Q_LSB = %b | Y = %d", 
                 $time, clk, rst, A, B, load_A, load_B, load_add, shift_HQ_LQ_Q_1, add_sub, Q_LSB, Y);
    end
    
    // Procedimiento de prueba
    initial begin
        // Inicialización
        clk = 0;
        rst = 0;
        load_A = 0;
        load_B = 0;
        load_add = 0;
        shift_HQ_LQ_Q_1 = 0;
        add_sub = 0;
        A = 8'd0;
        B = 8'd0;
        
        // Reset
        rst = 1;
        #10 rst = 0;
        #10 rst = 1;

        // Cargar valores en A y B
        A = 12'd15;   // Valor de prueba para A
        B = 12'd3;    // Valor de prueba para B
        load_A = 1;
        #10 load_A = 0;
        load_B = 1;
        #10 load_B = 0;

        // Iniciar la secuencia de multiplicación
        repeat (N) begin
            if (Q_LSB == 2'b01) begin
                // Si Q_LSB indica el valor de bit para suma
                add_sub = 1;     // Seleccionar suma
                load_add = 1;    // Cargar resultado de la suma
                #10 load_add = 0;
            end
            else if (Q_LSB == 2'b10) begin
                // Si Q_LSB indica el valor de bit para resta
                add_sub = 0;     // Seleccionar resta
                load_add = 1;    // Cargar resultado de la resta
                #10 load_add = 0;
            end
            
            // Desplazamiento aritmético a la derecha
            shift_HQ_LQ_Q_1 = 1;
            #10 shift_HQ_LQ_Q_1 = 0;
            #10;
        end
        
        // Verificar el resultado en Y
        $display("Resultado de la multiplicación: A = %d, B = %d, Y = %d", A, B, Y);
        
        // Finalizar la simulación
        #10 $stop;
    end
initial begin
    $dumpfile("tb_mult_with_no_fsm.vcd");  // Nombre del archivo de salida VCD
    $dumpvars(0, tb_mult_with_no_fsm);     // Registrar todas las señales del testbench actual
end

endmodule

src/build/tb_mult_with_no_fsm.vcd
$date
	Fri Nov 01 18:57:23 2024
$end
$version
	Icarus Verilog
$end
$timescale
	1ps
$end
$scope module tb_mult_with_no_fsm $end
$var wire 24 ! Y [23:0] $end
$var wire 2 " Q_LSB [1:0] $end
$var parameter 32 # N $end
$var reg 12 $ A [11:0] $end
$var reg 12 % B [11:0] $end
$var reg 1 & add_sub $end
$var reg 1 ' clk $end
$var reg 1 ( load_A $end
$var reg 1 ) load_B $end
$var reg 1 * load_add $end
$var reg 1 + rst $end
$var reg 1 , shift_HQ_LQ_Q_1 $end
$scope module uut $end
$var wire 12 - A [11:0] $end
$var wire 12 . B [11:0] $end
$var wire 1 & add_sub $end
$var wire 1 ' clk $end
$var wire 1 ( load_A $end
$var wire 1 ) load_B $end
$var wire 1 * load_add $end
$var wire 1 + rst $end
$var wire 1 , shift_HQ_LQ_Q_1 $end
$var parameter 32 / N $end
$var reg 12 0 HQ [11:0] $end
$var reg 12 1 LQ [11:0] $end
$var reg 12 2 M [11:0] $end
$var reg 1 3 Q_1 $end
$var reg 2 4 Q_LSB [1:0] $end
$var reg 24 5 Y [23:0] $end
$var reg 12 6 adder_sub_out [11:0] $end
$var reg 25 7 shift [24:0] $end
$upscope $end
$upscope $end
$enddefinitions $end
$comment Show the parameter values. $end
$dumpall
b1100 /
b1100 #
$end
#0
$dumpvars
bx 7
bx 6
bx 5
bx 4
x3
bx 2
bx 1
bx 0
b0 .
b0 -
0,
1+
0*
0)
0(
0'
0&
b0 %
b0 $
bx "
bx !
$end
#5000
1'
#10000
0'
0+
#15000
b0 6
b0 "
b0 4
b0 !
b0 5
03
b0 1
b0 0
b0 7
b0 2
1'
#20000
0'
1(
b11 %
b11 .
b1111 $
b1111 -
1+
#25000
b111111110001 6
b1111 2
1'
#30000
0'
1)
0(
#35000
b10 "
b10 4
b11 !
b11 5
b11 1
b110 7
1'
#40000
0'
1*
0)
#45000
b111111100010 6
b111111110001000000000011 !
b111111110001000000000011 5
b111111110001 0
b1111111100010000000000110 7
1'
#50000
0'
1,
0*
#55000
b111111101001 6
b11 "
b11 4
b111111111000100000000001 !
b111111111000100000000001 5
13
b100000000001 1
b111111111000 0
b1111111110001000000000011 7
1'
#60000
0'
0,
#65000
1'
#70000
0'
1,
#75000
b111111101101 6
b1 "
b1 4
b111111111100010000000000 !
b111111111100010000000000 5
b10000000000 1
b111111111100 0
b1111111111000100000000001 7
1'
#80000
0'
0,
#85000
1'
#90000
b1011 6
0'
1*
1&
#95000
b11010 6
b1011010000000000 !
b1011010000000000 5
b1011 0
b10110100000000001 7
1'
#100000
0'
1,
0*
#105000
b10100 6
b0 "
b0 4
b101101000000000 !
b101101000000000 5
03
b101000000000 1
b101 0
b1011010000000000 7
1'
#110000
0'
0,
#115000
1'
#120000
0'
1,
#125000
b10001 6
b10110100000000 !
b10110100000000 5
b110100000000 1
b10 0
b101101000000000 7
1'
#130000
0'
0,
#135000
1'
#140000
0'
1,
#145000
b10000 6
b1011010000000 !
b1011010000000 5
b11010000000 1
b1 0
b10110100000000 7
1'
#150000
0'
0,
#155000
1'
#160000
0'
1,
#165000
b1111 6
b101101000000 !
b101101000000 5
b101101000000 1
b0 0
b1011010000000 7
1'
#170000
0'
0,
#175000
1'
#180000
0'
1,
#185000
b10110100000 !
b10110100000 5
b10110100000 1
b101101000000 7
1'
#190000
0'
0,
#195000
1'
#200000
0'
1,
#205000
b1011010000 !
b1011010000 5
b1011010000 1
b10110100000 7
1'
#210000
0'
0,
#215000
1'
#220000
0'
1,
#225000
b101101000 !
b101101000 5
b101101000 1
b1011010000 7
1'
#230000
0'
0,
#235000
1'
#240000
0'
1,
#245000
b10110100 !
b10110100 5
b10110100 1
b101101000 7
1'
#250000
0'
0,
#255000
1'
#260000
0'
1,
#265000
b1011010 !
b1011010 5
b1011010 1
b10110100 7
1'
#270000
0'
0,
#275000
1'
#280000
0'
1,
#285000
b10 "
b10 4
b101101 !
b101101 5
b101101 1
b1011010 7
1'
#290000
0'
0,
